{
  "id": "98591713-4eb8-4a93-844e-0564e7f5e195",
  "repo": "usestrix/strix",
  "url": "https://github.com/usestrix/strix",
  "category": "Security/Pentest",
  "summary": "Công cụ pentest mã nguồn mở sử dụng trí tuệ nhân tạo để phát hiện và sửa chữa các lỗ hổng ứng dụng. Hỗ trợ các cuộc tấn công mô phỏng và tự động hóa quy trình kiểm tra bảo mật.",
  "usecases": [
    "Các chuyên gia an ninh muống tìm và khai thác lỗ hổng trong ứng dụng web",
    "Các công ty phần mềm cần tích hợp kiểm tra bảo mật vào quy trình CI/CD",
    "Câu lạc bộ hackathon CTF dùng để đào tạo thành viên"
  ],
  "ideas": [
    "Tích hợp với hệ thống SIEM để đe dọa phát hiện tự động",
    "Sử dụng trong môi trường đám mây để thực hiện pentest không cần thiết lập hạ tầng",
    "Kết hợp với công cụ bug bounty để tự động gửi báo cáo lỗ hổng"
  ],
  "stars": 29924,
  "starsToday": 1211,
  "language": "Python",
  "notePath": "notes/Security-Pentest.md",
  "createdAt": "2026-07-02T03:34:51.966Z"
}